{
  "camera": {
    "position": [
      2.4589770018513506,
      2.860654894841967,
      5.5526565404246995
    ],
    "focal_point": [
      0.0,
      0.0,
      0.0
    ],
    "view_up": [
      -0.05222475433592076,
      0.8969764243458335,
      -0.4389827664069696
    ],
    "view_angle": 30.0,
    "clipping_range": [
      3.35461563153594,
      10.95629183002395
    ]
  },
  "mesh": {
    "position": [
      0.0,
      0.0,
      0.0
    ],
    "transform_matrix": [
      [
        1.0,
        0.0,
        0.0,
        0.0
      ],
      [
        0.0,
        1.0,
        0.0,
        0.0
      ],
      [
        0.0,
        0.0,
        1.0,
        0.0
      ],
      [
        0.0,
        0.0,
        0.0,
        1.0
      ]
    ],
    "color": "#1E5F8E",
    "linewidth": 4,
    "edge_color": [
      0.3686274509803922,
      0.7019607843137254,
      0.9921568627450981
    ]
  },
  "viewport": {
    "size": [
      2552,
      1432
    ],
    "background_color": "#0A2239"
  },
  "svg": {
    "name": "blueprint",
    "stroke_width": 8,
    "background": "#0A2239",
    "fill": "#1E5F8E",
    "stroke": "#5EB3FD",
    "stroke_linecap": "round",
    "stroke_linejoin": "round"
  }
}